libcurl_ext/__init__.py
libcurl_ext/py.typed
libcurl_ext-0.1.0.dist-info/WHEEL
libcurl_ext-0.1.0.dist-info/METADATA
libcurl_ext-0.1.0.dist-info/RECORD
