Metadata-Version: 2.3
Name: libcurl-ext
Version: 0.1.0
Summary: Python bindings for libcurl
Author: Faddeev-Popov
Author-email: Faddeev-Popov <faddeev-popov@proton.me>
Requires-Python: >=3.13
